signalwire_agents/__init__.py
signalwire_agents/agent_server.py
signalwire_agents/schema.json
signalwire_agents/agents/bedrock.py
signalwire_agents/cli/__init__.py
signalwire_agents/cli/build_search.py
signalwire_agents/cli/config.py
signalwire_agents/cli/dokku.py
signalwire_agents/cli/init_project.py
signalwire_agents/cli/swaig_test_wrapper.py
signalwire_agents/cli/test_swaig.py
signalwire_agents/cli/types.py
signalwire_agents/cli/core/__init__.py
signalwire_agents/cli/core/agent_loader.py
signalwire_agents/cli/core/argparse_helpers.py
signalwire_agents/cli/core/dynamic_config.py
signalwire_agents/cli/core/service_loader.py
signalwire_agents/cli/execution/__init__.py
signalwire_agents/cli/execution/datamap_exec.py
signalwire_agents/cli/execution/webhook_exec.py
signalwire_agents/cli/output/__init__.py
signalwire_agents/cli/output/output_formatter.py
signalwire_agents/cli/output/swml_dump.py
signalwire_agents/cli/simulation/__init__.py
signalwire_agents/cli/simulation/data_generation.py
signalwire_agents/cli/simulation/data_overrides.py
signalwire_agents/cli/simulation/mock_env.py
signalwire_agents/core/__init__.py
signalwire_agents/core/agent_base.py
signalwire_agents/core/auth_handler.py
signalwire_agents/core/config_loader.py
signalwire_agents/core/contexts.py
signalwire_agents/core/data_map.py
signalwire_agents/core/function_result.py
signalwire_agents/core/logging_config.py
signalwire_agents/core/pom_builder.py
signalwire_agents/core/security_config.py
signalwire_agents/core/skill_base.py
signalwire_agents/core/skill_manager.py
signalwire_agents/core/swaig_function.py
signalwire_agents/core/swml_builder.py
signalwire_agents/core/swml_handler.py
signalwire_agents/core/swml_renderer.py
signalwire_agents/core/swml_service.py
signalwire_agents/core/agent/__init__.py
signalwire_agents/core/agent/config/__init__.py
signalwire_agents/core/agent/deployment/__init__.py
signalwire_agents/core/agent/deployment/handlers/__init__.py
signalwire_agents-1.0.18.dist-info/licenses/LICENSE
signalwire_agents-1.0.18.dist-info/METADATA
signalwire_agents-1.0.18.dist-info/WHEEL
signalwire_agents-1.0.18.dist-info/entry_points.txt
signalwire_agents-1.0.18.dist-info/top_level.txt
signalwire_agents-1.0.18.dist-info/RECORD
