Metadata-Version: 2.4
Name: signalwire_agents
Version: 1.0.18
Summary: SignalWire AI Agents SDK
Author-email: SignalWire Team <info@signalwire.com>
License: MIT
Project-URL: Homepage, https://github.com/signalwire/signalwire-agents
Keywords: signalwire,ai,agents,voice,telephony,swaig,swml
Classifier: Development Status :: 4 - Beta
Classifier: Intended Audience :: Developers
Classifier: License :: OSI Approved :: MIT License
Classifier: Programming Language :: Python :: 3
Classifier: Programming Language :: Python :: 3.7
Classifier: Programming Language :: Python :: 3.8
Classifier: Programming Language :: Python :: 3.9
Classifier: Programming Language :: Python :: 3.10
Classifier: Programming Language :: Python :: 3.11
Requires-Python: >=3.7
License-File: LICENSE
Requires-Dist: fastapi>=0.115.12
Requires-Dist: pydantic>=2.11.4
Requires-Dist: PyYAML>=6.0.2
Requires-Dist: Requests>=2.32.3
Requires-Dist: setuptools<81,>=66.1.1
Requires-Dist: signalwire_pom>=2.7.1
Requires-Dist: structlog>=25.3.0
Requires-Dist: uvicorn>=0.34.2
Requires-Dist: beautifulsoup4>=4.12.3
Requires-Dist: pytz>=2023.3
Requires-Dist: lxml>=4.9.0
Provides-Extra: search-queryonly
Requires-Dist: numpy>=1.24.0; extra == "search-queryonly"
Requires-Dist: scikit-learn>=1.3.0; extra == "search-queryonly"
Requires-Dist: sentence-transformers>=2.2.0; extra == "search-queryonly"
Requires-Dist: nltk>=3.8; extra == "search-queryonly"
Provides-Extra: search
Requires-Dist: sentence-transformers>=2.2.0; extra == "search"
Requires-Dist: scikit-learn>=1.3.0; extra == "search"
Requires-Dist: nltk>=3.8; extra == "search"
Requires-Dist: numpy>=1.24.0; extra == "search"
Provides-Extra: search-full
Requires-Dist: sentence-transformers>=2.2.0; extra == "search-full"
Requires-Dist: scikit-learn>=1.3.0; extra == "search-full"
Requires-Dist: nltk>=3.8; extra == "search-full"
Requires-Dist: numpy>=1.24.0; extra == "search-full"
Requires-Dist: pdfplumber>=0.9.0; extra == "search-full"
Requires-Dist: python-docx>=0.8.11; extra == "search-full"
Requires-Dist: markdown>=3.4.0; extra == "search-full"
Requires-Dist: striprtf>=0.0.26; extra == "search-full"
Requires-Dist: openpyxl>=3.1.0; extra == "search-full"
Requires-Dist: python-pptx>=0.6.21; extra == "search-full"
Requires-Dist: python-magic>=0.4.27; extra == "search-full"
Provides-Extra: search-nlp
Requires-Dist: sentence-transformers>=2.2.0; extra == "search-nlp"
Requires-Dist: scikit-learn>=1.3.0; extra == "search-nlp"
Requires-Dist: nltk>=3.8; extra == "search-nlp"
Requires-Dist: numpy>=1.24.0; extra == "search-nlp"
Requires-Dist: spacy>=3.6.0; extra == "search-nlp"
Provides-Extra: search-all
Requires-Dist: sentence-transformers>=2.2.0; extra == "search-all"
Requires-Dist: scikit-learn>=1.3.0; extra == "search-all"
Requires-Dist: nltk>=3.8; extra == "search-all"
Requires-Dist: numpy>=1.24.0; extra == "search-all"
Requires-Dist: spacy>=3.6.0; extra == "search-all"
Requires-Dist: pdfplumber>=0.9.0; extra == "search-all"
Requires-Dist: python-docx>=0.8.11; extra == "search-all"
Requires-Dist: markdown>=3.4.0; extra == "search-all"
Requires-Dist: striprtf>=0.0.26; extra == "search-all"
Requires-Dist: openpyxl>=3.1.0; extra == "search-all"
Requires-Dist: python-pptx>=0.6.21; extra == "search-all"
Requires-Dist: python-magic>=0.4.27; extra == "search-all"
Requires-Dist: psycopg2-binary>=2.9.0; extra == "search-all"
Requires-Dist: pgvector>=0.2.0; extra == "search-all"
Provides-Extra: pgvector
Requires-Dist: psycopg2-binary>=2.9.0; extra == "pgvector"
Requires-Dist: pgvector>=0.2.0; extra == "pgvector"
Provides-Extra: mcp-gateway
Requires-Dist: flask>=2.0.0; extra == "mcp-gateway"
Requires-Dist: flask-limiter>=3.5.0; extra == "mcp-gateway"
Provides-Extra: all
Requires-Dist: sentence-transformers>=2.2.0; extra == "all"
Requires-Dist: scikit-learn>=1.3.0; extra == "all"
Requires-Dist: nltk>=3.8; extra == "all"
Requires-Dist: numpy>=1.24.0; extra == "all"
Requires-Dist: spacy>=3.6.0; extra == "all"
Requires-Dist: pdfplumber>=0.9.0; extra == "all"
Requires-Dist: python-docx>=0.8.11; extra == "all"
Requires-Dist: markdown>=3.4.0; extra == "all"
Requires-Dist: striprtf>=0.0.26; extra == "all"
Requires-Dist: openpyxl>=3.1.0; extra == "all"
Requires-Dist: python-pptx>=0.6.21; extra == "all"
Requires-Dist: python-magic>=0.4.27; extra == "all"
Dynamic: license-file
